
1. Deklaracje klas:
   Java: public class Bubble  
   Kotlin: public final class Bubble
  Różnica polega na tym, że w języku Kotlin klasa jest oznaczona jako final, co oznacza, że nie może mieć podklas.
2. Instrukcje związane z adnotacjami:
   Kotlin: występują adnotacje, takie jak @Lkotlin/Metadata, @Lorg/jetbrains/annotations/NotNull, @Lkotlin/jvm/JvmStatic, @Lkotlin/Metadata.
   Java: nie występują adnotacje.
3. Instrukcje związane z obsługą wyjątków:
  Kotlin: brak instrukcji dotyczących obsługi wyjątków, takich jak try-catch czy throw.
  Java: brak obsługi wyjątków w tym konkretnym kodzie, ale ogólnie język Java obsługuje wyjątki za pomocą instrukcji try-catch i throw.
4. Instrukcje związane z porównywaniem wartości:
  Kotlin: używane jest IF_ICMPLE do porównywania wartości (na przykład w instrukcji warunkowej if).
  Java: używane jest IF_ICMPGE do porównywania wartości (na przykład w instrukcji warunkowej if).
5. Instrukcje związane z obsługą nulli:
  Kotlin: występują instrukcje związane z obsługą nulli, takie jak checkNotNullParameter, które są wywoływane przy użyciu adnotacji @Lorg/jetbrains/annotations/NotNull.
  Java: brak instrukcji związanych z obsługą nulli w tym konkretnym kodzie, ale język Java obsługuje null za pomocą instrukcji null-check.
6. Oznaczanie metody jako statycznej:
  Kotlin: metoda main jest oznaczona adnotacją @Lkotlin/jvm/JvmStatic, co oznacza, że jest to metoda statyczna.
  Java: metoda main jest statyczna przez konwencję, ale nie ma dodatkowych adnotacji.


// class version 52.0 (52)
// access flags 0x31
public final class Bubble {

  // compiled from: Bubble.kt

  @Lkotlin/Metadata;(mv={1, 8, 0}, k=1, xi=48, d1={"\u0000&\n\u0002\u0018\u0002\n\u0002\u0010\u0000\n\u0002\u0008\u0002\n\u0002\u0010\u0002\n\u0000\n\u0002\u0010\u0015\n\u0002\u0008\u0002\n\u0002\u0010\u0011\n\u0002\u0010\u000e\n\u0002\u0008\u0002\u0008\u00c6\u0002\u0018\u00002\u00020\u0001B\u0007\u0008\u0002\u00a2\u0006\u0002\u0010\u0002J\u000e\u0010\u0003\u001a\u00020\u00042\u0006\u0010\u0005\u001a\u00020\u0006J\u001b\u0010\u0007\u001a\u00020\u00042\u000c\u0010\u0008\u001a\u0008\u0012\u0004\u0012\u00020\n0\u0009H\u0007\u00a2\u0006\u0002\u0010\u000b\u00a8\u0006\u000c"}, d2={"LBubble;", "", "()V", "bubbleSort", "", "arr", "", "main", "args", "", "", "([Ljava/lang/String;)V", "untitled1"})

  // access flags 0x19
  public final static LBubble; INSTANCE
  @Lorg/jetbrains/annotations/NotNull;() // invisible

  // access flags 0x2
  private <init>()V
   L0
    LINENUMBER 1 L0
    ALOAD 0
    INVOKESPECIAL java/lang/Object.<init> ()V
    RETURN
   L1
    LOCALVARIABLE this LBubble; L0 L1 0
    MAXSTACK = 1
    MAXLOCALS = 1

  // access flags 0x11
  public final bubbleSort([I)V
    // annotable parameter count: 1 (invisible)
    @Lorg/jetbrains/annotations/NotNull;() // invisible, parameter 0
   L0
    ALOAD 1
    LDC "arr"
    INVOKESTATIC kotlin/jvm/internal/Intrinsics.checkNotNullParameter (Ljava/lang/Object;Ljava/lang/String;)V
   L1
    LINENUMBER 3 L1
    ALOAD 1
    ARRAYLENGTH
    ISTORE 2
   L2
    LINENUMBER 4 L2
    ICONST_0
    ISTORE 3
   L3
    LINENUMBER 5 L3
    ICONST_0
    ISTORE 4
   L4
   FRAME APPEND [I I I]
    ILOAD 4
    ILOAD 2
    IF_ICMPGE L5
   L6
    LINENUMBER 6 L6
    ICONST_1
    ISTORE 5
   L7
    ILOAD 2
    ILOAD 4
    ISUB
    ISTORE 6
   L8
   FRAME APPEND [I I]
    ILOAD 5
    ILOAD 6
    IF_ICMPGE L9
   L10
    LINENUMBER 7 L10
    ALOAD 1
    ILOAD 5
    ICONST_1
    ISUB
    IALOAD
    ALOAD 1
    ILOAD 5
    IALOAD
    IF_ICMPLE L11
   L12
    LINENUMBER 9 L12
    ALOAD 1
    ILOAD 5
    ICONST_1
    ISUB
    IALOAD
    ISTORE 3
   L13
    LINENUMBER 10 L13
    ALOAD 1
    ILOAD 5
    ICONST_1
    ISUB
    ALOAD 1
    ILOAD 5
    IALOAD
    IASTORE
   L14
    LINENUMBER 11 L14
    ALOAD 1
    ILOAD 5
    ILOAD 3
    IASTORE
   L11
    LINENUMBER 6 L11
   FRAME SAME
    IINC 5 1
    GOTO L8
   L9
    LINENUMBER 5 L9
   FRAME SAME
    IINC 4 1
    GOTO L4
   L5
    LINENUMBER 15 L5
   FRAME CHOP 2
    RETURN
   L15
    LOCALVARIABLE j I L7 L9 5
    LOCALVARIABLE i I L4 L5 4
    LOCALVARIABLE n I L2 L15 2
    LOCALVARIABLE temp I L3 L15 3
    LOCALVARIABLE this LBubble; L0 L15 0
    LOCALVARIABLE arr [I L0 L15 1
    MAXSTACK = 4
    MAXLOCALS = 7

  // access flags 0x19
  public final static main([Ljava/lang/String;)V
  @Lkotlin/jvm/JvmStatic;()
    // annotable parameter count: 1 (invisible)
    @Lorg/jetbrains/annotations/NotNull;() // invisible, parameter 0
   L0
    ALOAD 0
    LDC "args"
    INVOKESTATIC kotlin/jvm/internal/Intrinsics.checkNotNullParameter (Ljava/lang/Object;Ljava/lang/String;)V
   L1
    LINENUMBER 19 L1
    BIPUSH 7
    NEWARRAY T_INT
    ASTORE 2
    ALOAD 2
    ICONST_0
    ICONST_3
    IASTORE
    ALOAD 2
    ICONST_1
    BIPUSH 60
    IASTORE
    ALOAD 2
    ICONST_2
    BIPUSH 35
    IASTORE
    ALOAD 2
    ICONST_3
    ICONST_2
    IASTORE
    ALOAD 2
    ICONST_4
    BIPUSH 45
    IASTORE
    ALOAD 2
    ICONST_5
    SIPUSH 320
    IASTORE
    ALOAD 2
    BIPUSH 6
    ICONST_5
    IASTORE
    ALOAD 2
    ASTORE 1
   L2
    LINENUMBER 21 L2
    GETSTATIC Bubble.INSTANCE : LBubble;
    ALOAD 1
    INVOKEVIRTUAL Bubble.bubbleSort ([I)V
   L3
    LINENUMBER 23 L3
    RETURN
   L4
    LOCALVARIABLE arr [I L2 L4 1
    LOCALVARIABLE args [Ljava/lang/String; L0 L4 0
    MAXSTACK = 3
    MAXLOCALS = 3

  // access flags 0x8
  static <clinit>()V
    NEW Bubble
    DUP
    INVOKESPECIAL Bubble.<init> ()V
    PUTSTATIC Bubble.INSTANCE : LBubble;
    RETURN
    MAXSTACK = 2
    MAXLOCALS = 0
}
